{
  "positions": {
    "qb": [
      "Lamar Jackson (BAL)",
      "Tua Tagovailoa (MIA)",
      "Caleb Williams (CHI)",
      "Joe Burrow (CIN)",
      "Sam Darnold (SEA)",
      "Jayden Daniels (WAS)",
      "Dak Prescott (DAL)",
      "Kyler Murray (ARI)"
    ],
    "rb": [
      "Derrick Henry (BAL)",
      "Keaton Mitchell (BAL)",
      "Justice Hill (BAL)",

      "De'Von Achane (MIA)",
      "Ollie Gordon II  (MIA)",
      "Jaylen Wright (MIA)",

      "D'Andre Swift (CHI)",
      "Kyle Monangai (CHI)",
      "Roschon Johnson (CHI)",

      "Samaje Perine (CIN)",
      "Chase Brown (CIN)",
      "Tahj Brooks (CIN)",

      "Kenneth Walker III (SEA)",
      "Zach Charbonnet (SEA)",
      "George Holani  (SEA)",

      "Jacory Croskey-Merritt (WAS)",
      "Jeremy McNichols (WAS)",
      "Chris Rodriguez Jr. (WAS)",

      "Javonte Williams (DAL)",
      "Jaydon Blue (DAL)",
      "Hunter Luepke  (DAL)",

      "Bam Knight (ARI)",
      "Emari Demercado (ARI)",
      "Your mom (ARI)"
    ],
    "wr": [
      "Zay Flowers (BAL)",
      "Rashod Bateman (BAL)",
      "DeAndre Hopkins (BAL)",
      "Devontez Walker (BAL)",
      "Tylan Wallace (BAL)",

      "Tyreek Hill (MIA)",
      "Malik Washington (MIA)",
      "Nick Westbrook-Ikhine (MIA)",
      "Dee Eskridge (MIA)",
      "Cedrick Wilson Jr.(MIA)",

      "Rome Odunze (CHI)",
      "DJ Moore  (CHI)",
      "Olamide Zaccheaus (CHI)",
      "Luther Burden III (CHI)",
      "Devin Duvernay (CHI)",

      "Ja'Marr Chase (CIN)",
      "Tee Higgins (CIN)",
      "Jermaine Burton (CIN)",
      "Mitchell Tinsley (CIN)",
      "Trenton Irwin (CIN)",

      "Jaxon Smith-Njigba (SEA)",
      "Cooper Kupp (SEA)",
      "Tory Horton (SEA)",
      "Jake Bobo (SEA)",
      "Dareke Young (SEA)",

      "Terry McLaurin (WAS)",
      "Deebo Samuel (WAS)",
      "Luke McCaffrey (WAS)",
      "Chris Moore (WAS)",
      "Jaylin Lane (WAS)",

      "CeeDee Lamb (DAL)",
      "George Pickens (DAL)",
      "Jalen Tolbert (DAL)",
      "KaVontae Turpin (DAL)",
      "Jonathan Mingo (DAL)",

      "Marvin Harrison Jr. (ARI)",
      "Michael Wilson (ARI)",
      "Zay Jones (ARI)",
      "Greg Dortch (ARI)",
      "Xavier Weaver (ARI)"
    ],
    "te": [
      "Mark Andrews (BAL)",
      "Isaiah Likely (BAL)",

      "Greg Dulciche (MIA)",
      "Tanner Conner (MIA)",

      "Cole Kmet (CHI)",
      "Coleston Loveland (CHI)",

      "Noah Fant (CIN)",
      "Tanner Hudson (CIN)",

      "AJ Barner (SEA)",
      "Elijah Arroyo (SEA)",

      "Zach Ertz (WAS)",
      "Ben Sinnott (WAS)",

      "Jake Ferguson (DAL)",
      "Luke Schoonmaker (DAL)",

      "Trey McBride (ARI)",
      "Elijah Higgins (ARI)"
    ],
    "k": [
      "Tyler Loop (BAL)",
      "Jason Sanders (MIA)",
      "Cairo Santos (CHI)",
      "Evan McPherson (CIN)",
      "Jason Myers (SEA)",
      "Matt Gay (WAS)",
      "Brandon Aubrey (DAL)",
      "Chad Ryland (ARI)"
    ]
  }
}
